legos_command
nuget
