Metadata-Version: 1.0
Name: xamarin-legos
Version: 1.0.3
Summary: command line tool to fetch details from github projects/nuget packages
Home-page: https://github.com/prashantvc/legos-cli
Author: Prashant Cholachagudda
Author-email: pvc@outlook.com
License: UNKNOWN
Platform: UNKNOWN
